vja/__init__.py
vja/apiclient.py
vja/authenticate.py
vja/cli.py
vja/config.py
vja/filter.py
vja/model.py
vja/output.py
vja/parse.py
vja/project_service.py
vja/service_command.py
vja/service_query.py
vja/task_service.py
vja/urgency.py
vja-4.10.1.dist-info/licenses/LICENSE
vja-4.10.1.dist-info/METADATA
vja-4.10.1.dist-info/WHEEL
vja-4.10.1.dist-info/entry_points.txt
vja-4.10.1.dist-info/top_level.txt
vja-4.10.1.dist-info/RECORD
