Metadata-Version: 2.4
Name: vja
Version: 4.10.1
Summary: A simple CLI for Vikunja task manager
Author: ce72
License: GNU General Public License v3 (GPLv3)
Classifier: Environment :: Console
Classifier: Intended Audience :: End Users/Desktop
Classifier: Programming Language :: Python :: 3.9
Classifier: Programming Language :: Python :: 3.10
Classifier: Programming Language :: Python :: 3.11
Classifier: Programming Language :: Python :: 3.12
Classifier: Programming Language :: Python :: 3.13
Classifier: License :: OSI Approved :: GNU General Public License v3 (GPLv3)
Requires-Python: >=3.9
License-File: LICENSE
Requires-Dist: click>=8.1
Requires-Dist: click-aliases>=1
Requires-Dist: requests>=2.32
Requires-Dist: parsedatetime>=2.6
Requires-Dist: python-dateutil>=2.8
Dynamic: license-file
